{
  "description": "TYPE: CUSTOM\nMaterial Theme Builder export",
  "seed": "#6750A4",
  "coreColors": {
    "primary": "#6750A4"
  },
  "extendedColors": [],
  "schemes": {
    "light": {
      "primaryPaletteKeyColor": "#7A7484",
      "secondaryPaletteKeyColor": "#7A757F",
      "tertiaryPaletteKeyColor": "#7B748A",
      "neutralPaletteKeyColor": "#797678",
      "neutralVariantPaletteKeyColor": "#797678",
      "errorPaletteKeyColor": "#DE3730",
      "background": "#FDF8FA",
      "onBackground": "#1C1B1D",
      "surface": "#FDF8FA",
      "surfaceDim": "#DDD9DB",
      "surfaceBright": "#FDF8FA",
      "surfaceContainerLowest": "#FFFFFF",
      "surfaceContainerLow": "#F7F2F4",
      "surfaceContainer": "#F1EDEE",
      "surfaceContainerHigh": "#EBE7E9",
      "surfaceContainerHighest": "#E6E1E3",
      "onSurface": "#1C1B1D",
      "surfaceVariant": "#E6E1E3",
      "onSurfaceVariant": "#484648",
      "inverseSurface": "#313032",
      "inverseOnSurface": "#F4EFF1",
      "outline": "#797678",
      "outlineVariant": "#C9C5C7",
      "shadow": "#000000",
      "scrim": "#000000",
      "surfaceTint": "#615C6B",
      "primary": "#615C6B",
      "primaryDim": "#6B6575",
      "onPrimary": "#FFFFFF",
      "primaryContainer": "#494453",
      "onPrimaryContainer": "#B9B2C4",
      "inversePrimary": "#CBC3D5",
      "primaryFixed": "#E7DFF2",
      "primaryFixedDim": "#CBC3D5",
      "onPrimaryFixed": "#1D1A26",
      "onPrimaryFixedVariant": "#494453",
      "secondary": "#615D66",
      "secondaryDim": "#6A6670",
      "onSecondary": "#FFFFFF",
      "secondaryContainer": "#49454E",
      "onSecondaryContainer": "#B9B3BE",
      "secondaryFixed": "#E7E0EB",
      "secondaryFixedDim": "#CAC4CF",
      "onSecondaryFixed": "#1D1A22",
      "onSecondaryFixedVariant": "#49454E",
      "tertiary": "#625B71",
      "tertiaryDim": "#6B647A",
      "onTertiary": "#FFFFFF",
      "tertiaryContainer": "#4A4458",
      "onTertiaryContainer": "#BAB1CA",
      "tertiaryFixed": "#E8DEF8",
      "tertiaryFixedDim": "#CBC2DB",
      "onTertiaryFixed": "#1E192B",
      "onTertiaryFixedVariant": "#4A4458",
      "error": "#BA1A1A",
      "errorDim": "#AC0C12",
      "onError": "#FFFFFF",
      "errorContainer": "#93000A",
      "onErrorContainer": "#FF9A8E"
    },
    "light-medium-contrast": {
      "primaryPaletteKeyColor": "#7A7484",
      "secondaryPaletteKeyColor": "#7A757F",
      "tertiaryPaletteKeyColor": "#7B748A",
      "neutralPaletteKeyColor": "#797678",
      "neutralVariantPaletteKeyColor": "#797678",
      "errorPaletteKeyColor": "#DE3730",
      "background": "#FDF8FA",
      "onBackground": "#1C1B1D",
      "surface": "#FDF8FA",
      "surfaceDim": "#C9C5C7",
      "surfaceBright": "#FDF8FA",
      "surfaceContainerLowest": "#FFFFFF",
      "surfaceContainerLow": "#F7F2F4",
      "surfaceContainer": "#EBE7E9",
      "surfaceContainerHigh": "#E0DCDD",
      "surfaceContainerHighest": "#D5D0D2",
      "onSurface": "#121112",
      "surfaceVariant": "#E6E1E3",
      "onSurfaceVariant": "#373637",
      "inverseSurface": "#313032",
      "inverseOnSurface": "#F4EFF1",
      "outline": "#545253",
      "outlineVariant": "#6F6C6E",
      "shadow": "#000000",
      "scrim": "#000000",
      "surfaceTint": "#615C6B",
      "primary": "#383442",
      "primaryDim": "#474251",
      "onPrimary": "#FFFFFF",
      "primaryContainer": "#231F2C",
      "onPrimaryContainer": "#B0A9BA",
      "inversePrimary": "#CBC3D5",
      "primaryFixed": "#706A7A",
      "primaryFixedDim": "#575261",
      "onPrimaryFixed": "#FFFFFF",
      "onPrimaryFixedVariant": "#FFFFFF",
      "secondary": "#38353D",
      "secondaryDim": "#46434C",
      "onSecondary": "#FFFFFF",
      "secondaryContainer": "#222028",
      "onSecondaryContainer": "#AFAAB4",
      "secondaryFixed": "#6F6B75",
      "secondaryFixedDim": "#57535C",
      "onSecondaryFixed": "#FFFFFF",
      "onSecondaryFixedVariant": "#FFFFFF",
      "tertiary": "#393347",
      "tertiaryDim": "#474156",
      "onTertiary": "#FFFFFF",
      "tertiaryContainer": "#231E31",
      "onTertiaryContainer": "#B0A8C0",
      "tertiaryFixed": "#716A80",
      "tertiaryFixedDim": "#585267",
      "onTertiaryFixed": "#FFFFFF",
      "onTertiaryFixedVariant": "#FFFFFF",
      "error": "#740006",
      "errorDim": "#8F0009",
      "onError": "#FFFFFF",
      "errorContainer": "#4B0002",
      "onErrorContainer": "#FF8B7E"
    },
    "light-high-contrast": {
      "primaryPaletteKeyColor": "#7A7484",
      "secondaryPaletteKeyColor": "#7A757F",
      "tertiaryPaletteKeyColor": "#7B748A",
      "neutralPaletteKeyColor": "#797678",
      "neutralVariantPaletteKeyColor": "#797678",
      "errorPaletteKeyColor": "#DE3730",
      "background": "#FDF8FA",
      "onBackground": "#1C1B1D",
      "surface": "#FDF8FA",
      "surfaceDim": "#BBB8B9",
      "surfaceBright": "#FDF8FA",
      "surfaceContainerLowest": "#FFFFFF",
      "surfaceContainerLow": "#F4EFF1",
      "surfaceContainer": "#E6E1E3",
      "surfaceContainerHigh": "#D7D3D5",
      "surfaceContainerHighest": "#C9C5C7",
      "onSurface": "#000000",
      "surfaceVariant": "#E6E1E3",
      "onSurfaceVariant": "#000000",
      "inverseSurface": "#313032",
      "inverseOnSurface": "#FFFFFF",
      "outline": "#2D2C2D",
      "outlineVariant": "#4A494A",
      "shadow": "#000000",
      "scrim": "#000000",
      "surfaceTint": "#615C6B",
      "primary": "#2E2A38",
      "primaryDim": "#211D2A",
      "onPrimary": "#FFFFFF",
      "primaryContainer": "#191622",
      "onPrimaryContainer": "#D1C9DB",
      "inversePrimary": "#CBC3D5",
      "primaryFixed": "#4C4755",
      "primaryFixedDim": "#35313E",
      "onPrimaryFixed": "#FFFFFF",
      "onPrimaryFixedVariant": "#FFFFFF",
      "secondary": "#2E2B33",
      "secondaryDim": "#211E26",
      "onSecondary": "#FFFFFF",
      "secondaryContainer": "#19161E",
      "onSecondaryContainer": "#D0CAD5",
      "secondaryFixed": "#4B4851",
      "secondaryFixedDim": "#34313A",
      "onSecondaryFixed": "#FFFFFF",
      "onSecondaryFixedVariant": "#FFFFFF",
      "tertiary": "#2F293C",
      "tertiaryDim": "#221D2F",
      "onTertiary": "#FFFFFF",
      "tertiaryContainer": "#1A1527",
      "onTertiaryContainer": "#D1C8E1",
      "tertiaryFixed": "#4C465B",
      "tertiaryFixedDim": "#353043",
      "onTertiaryFixed": "#FFFFFF",
      "onTertiaryFixedVariant": "#FFFFFF",
      "error": "#600004",
      "errorDim": "#480002",
      "onError": "#FFFFFF",
      "errorContainer": "#390001",
      "onErrorContainer": "#FFBCB4"
    },
    "dark": {
      "primaryPaletteKeyColor": "#7A7484",
      "secondaryPaletteKeyColor": "#7A757F",
      "tertiaryPaletteKeyColor": "#7B748A",
      "neutralPaletteKeyColor": "#797678",
      "neutralVariantPaletteKeyColor": "#797678",
      "errorPaletteKeyColor": "#DE3730",
      "background": "#141314",
      "onBackground": "#E6E1E3",
      "surface": "#141314",
      "surfaceDim": "#141314",
      "surfaceBright": "#3A393A",
      "surfaceContainerLowest": "#0F0E0F",
      "surfaceContainerLow": "#1C1B1D",
      "surfaceContainer": "#201F21",
      "surfaceContainerHigh": "#2B292B",
      "surfaceContainerHighest": "#363436",
      "onSurface": "#E6E1E3",
      "surfaceVariant": "#484648",
      "onSurfaceVariant": "#C9C5C7",
      "inverseSurface": "#E6E1E3",
      "inverseOnSurface": "#313032",
      "outline": "#939092",
      "outlineVariant": "#484648",
      "shadow": "#000000",
      "scrim": "#000000",
      "surfaceTint": "#CBC3D5",
      "primary": "#CBC3D5",
      "primaryDim": "#D9D1E3",
      "onPrimary": "#322E3C",
      "primaryContainer": "#E7DFF2",
      "onPrimaryContainer": "#676271",
      "inversePrimary": "#615C6B",
      "primaryFixed": "#E7DFF2",
      "primaryFixedDim": "#CBC3D5",
      "onPrimaryFixed": "#1D1A26",
      "onPrimaryFixedVariant": "#494453",
      "secondary": "#CAC4CF",
      "secondaryDim": "#D8D2DD",
      "onSecondary": "#322F38",
      "secondaryContainer": "#E7E0EB",
      "onSecondaryContainer": "#67636C",
      "secondaryFixed": "#E7E0EB",
      "secondaryFixedDim": "#CAC4CF",
      "onSecondaryFixed": "#1D1A22",
      "onSecondaryFixedVariant": "#49454E",
      "tertiary": "#CBC2DB",
      "tertiaryDim": "#EEE4FE",
      "onTertiary": "#332D41",
      "tertiaryContainer": "#E8DEF8",
      "onTertiaryContainer": "#686177",
      "tertiaryFixed": "#E8DEF8",
      "tertiaryFixedDim": "#CBC2DB",
      "onTertiaryFixed": "#1E192B",
      "onTertiaryFixedVariant": "#4A4458",
      "error": "#FFB4AB",
      "errorDim": "#FFC7C0",
      "onError": "#690005",
      "errorContainer": "#FFDAD6",
      "onErrorContainer": "#C32220"
    },
    "dark-medium-contrast": {
      "primaryPaletteKeyColor": "#7A7484",
      "secondaryPaletteKeyColor": "#7A757F",
      "tertiaryPaletteKeyColor": "#7B748A",
      "neutralPaletteKeyColor": "#797678",
      "neutralVariantPaletteKeyColor": "#797678",
      "errorPaletteKeyColor": "#DE3730",
      "background": "#141314",
      "onBackground": "#E6E1E3",
      "surface": "#141314",
      "surfaceDim": "#141314",
      "surfaceBright": "#464446",
      "surfaceContainerLowest": "#080708",
      "surfaceContainerLow": "#1E1D1F",
      "surfaceContainer": "#292729",
      "surfaceContainerHigh": "#333234",
      "surfaceContainerHighest": "#3F3D3F",
      "onSurface": "#FFFFFF",
      "surfaceVariant": "#484648",
      "onSurfaceVariant": "#DFDBDD",
      "inverseSurface": "#E6E1E3",
      "inverseOnSurface": "#2B2A2B",
      "outline": "#B4B1B3",
      "outlineVariant": "#928F91",
      "shadow": "#000000",
      "scrim": "#000000",
      "surfaceTint": "#CBC3D5",
      "primary": "#E1D9EB",
      "primaryDim": "#D9D1E3",
      "onPrimary": "#272431",
      "primaryContainer": "#FDF7FF",
      "onPrimaryContainer": "#575261",
      "inversePrimary": "#4A4654",
      "primaryFixed": "#E7DFF2",
      "primaryFixedDim": "#CBC3D5",
      "onPrimaryFixed": "#130F1C",
      "onPrimaryFixedVariant": "#383442",
      "secondary": "#E0DAE5",
      "secondaryDim": "#D8D2DD",
      "onSecondary": "#27242D",
      "secondaryContainer": "#FDF7FF",
      "onSecondaryContainer": "#57535C",
      "secondaryFixed": "#E7E0EB",
      "secondaryFixedDim": "#CAC4CF",
      "onSecondaryFixed": "#121018",
      "onSecondaryFixedVariant": "#38353D",
      "tertiary": "#E2D8F2",
      "tertiaryDim": "#EEE4FE",
      "onTertiary": "#282336",
      "tertiaryContainer": "#FDF7FF",
      "onTertiaryContainer": "#585267",
      "tertiaryFixed": "#E8DEF8",
      "tertiaryFixedDim": "#CBC2DB",
      "onTertiaryFixed": "#130E20",
      "onTertiaryFixedVariant": "#393347",
      "error": "#FFD2CC",
      "errorDim": "#FFC7C0",
      "onError": "#540003",
      "errorContainer": "#FFF7F6",
      "onErrorContainer": "#AB0B12"
    },
    "dark-high-contrast": {
      "primaryPaletteKeyColor": "#7A7484",
      "secondaryPaletteKeyColor": "#7A757F",
      "tertiaryPaletteKeyColor": "#7B748A",
      "neutralPaletteKeyColor": "#797678",
      "neutralVariantPaletteKeyColor": "#797678",
      "errorPaletteKeyColor": "#DE3730",
      "background": "#141314",
      "onBackground": "#E6E1E3",
      "surface": "#141314",
      "surfaceDim": "#141314",
      "surfaceBright": "#514F51",
      "surfaceContainerLowest": "#000000",
      "surfaceContainerLow": "#201F21",
      "surfaceContainer": "#313032",
      "surfaceContainerHigh": "#3C3B3C",
      "surfaceContainerHighest": "#484648",
      "onSurface": "#FFFFFF",
      "surfaceVariant": "#484648",
      "onSurfaceVariant": "#FFFFFF",
      "inverseSurface": "#E6E1E3",
      "inverseOnSurface": "#000000",
      "outline": "#F3EFF1",
      "outlineVariant": "#C5C1C3",
      "shadow": "#000000",
      "scrim": "#000000",
      "surfaceTint": "#CBC3D5",
      "primary": "#E7DFF2",
      "primaryDim": "#FFFEFF",
      "onPrimary": "#000000",
      "primaryContainer": "#FFFFFF",
      "onPrimaryContainer": "#3E3947",
      "inversePrimary": "#4A4654",
      "primaryFixed": "#E7DFF2",
      "primaryFixedDim": "#CBC3D5",
      "onPrimaryFixed": "#000000",
      "onPrimaryFixedVariant": "#130F1C",
      "secondary": "#E7E0EB",
      "secondaryDim": "#FFFEFF",
      "onSecondary": "#000000",
      "secondaryContainer": "#FFFFFF",
      "onSecondaryContainer": "#3D3A43",
      "secondaryFixed": "#E7E0EB",
      "secondaryFixedDim": "#CAC4CF",
      "onSecondaryFixed": "#000000",
      "onSecondaryFixedVariant": "#121018",
      "tertiary": "#E8DEF8",
      "tertiaryDim": "#FFFEFF",
      "onTertiary": "#000000",
      "tertiaryContainer": "#FFFFFF",
      "onTertiaryContainer": "#3E384C",
      "tertiaryFixed": "#E8DEF8",
      "tertiaryFixedDim": "#CBC2DB",
      "onTertiaryFixed": "#000000",
      "onTertiaryFixedVariant": "#130E20",
      "error": "#FFDAD6",
      "errorDim": "#FFFEFF",
      "onError": "#000000",
      "errorContainer": "#FFFFFF",
      "onErrorContainer": "#7E0007"
    }
  },
  "palettes": {}
}